gplearn/__init__.py
gplearn/_program.py
gplearn/fitness.py
gplearn/functions.py
gplearn/genetic.py
gplearn/utils.py
gplearn/tests/__init__.py
gplearn/tests/test_estimator_checks.py
gplearn/tests/test_examples.py
gplearn/tests/test_fitness.py
gplearn/tests/test_functions.py
gplearn/tests/test_genetic.py
gplearn/tests/test_utils.py
gplearn-0.4.3.dist-info/METADATA
gplearn-0.4.3.dist-info/WHEEL
gplearn-0.4.3.dist-info/licenses/LICENSE
gplearn-0.4.3.dist-info/RECORD
