Metadata-Version: 2.4
Name: gplearn
Version: 0.4.3
Summary: Genetic Programming in Python, with a scikit-learn inspired API
Project-URL: homepage, https://gplearn.readthedocs.io/en/stable/
Project-URL: source, https://github.com/trevorstephens/gplearn
Project-URL: tracker, https://github.com/trevorstephens/gplearn/issues
Author-email: Trevor Stephens <trev.stephens@gmail.com>
License-Expression: BSD-3-Clause
License-File: LICENSE
Classifier: Development Status :: 3 - Alpha
Classifier: Intended Audience :: Developers
Classifier: Intended Audience :: Science/Research
Classifier: License :: OSI Approved
Classifier: Operating System :: MacOS
Classifier: Operating System :: Microsoft :: Windows
Classifier: Operating System :: Unix
Classifier: Programming Language :: Python
Classifier: Programming Language :: Python :: 3
Classifier: Programming Language :: Python :: 3.11
Classifier: Programming Language :: Python :: 3.12
Classifier: Programming Language :: Python :: 3.13
Classifier: Programming Language :: Python :: 3.14
Classifier: Topic :: Scientific/Engineering
Classifier: Topic :: Software Development
Requires-Python: >=3.11
Requires-Dist: joblib>=1.3.0
Requires-Dist: scikit-learn>=1.8.0
